Metadata-Version: 2.1
Name: iterable_utils
Version: 0.0.2
Summary: utils for iterable objects
Author: fleecy
Requires-Dist: numpy>=1.26.2
